pydeconstruct/__init__.py
pydeconstruct/cli.py
pydeconstruct/deconstruct.py
pydeconstruct-0.1.0.dist-info/licenses/LICENSE
pydeconstruct-0.1.0.dist-info/METADATA
pydeconstruct-0.1.0.dist-info/WHEEL
pydeconstruct-0.1.0.dist-info/entry_points.txt
pydeconstruct-0.1.0.dist-info/top_level.txt
pydeconstruct-0.1.0.dist-info/RECORD
