Metadata-Version: 2.4
Name: pydeconstruct
Version: 0.1.0
Summary: Deconstruct a Python file into C, assembly, and machine code
Author-email: Your Name <you@example.com>
License: MIT
Requires-Python: >=3.8
License-File: LICENSE
Requires-Dist: cython>=3.0
Dynamic: license-file
